vertex_ai_imagen/__init__.py
vertex_ai_imagen/client.py
vertex_ai_imagen/exceptions.py
vertex_ai_imagen/models.py
vertex_ai_imagen-1.1.4.dist-info/licenses/LICENSE
vertex_ai_imagen-1.1.4.dist-info/METADATA
vertex_ai_imagen-1.1.4.dist-info/WHEEL
vertex_ai_imagen-1.1.4.dist-info/top_level.txt
vertex_ai_imagen-1.1.4.dist-info/RECORD
