Metadata-Version: 2.4
Name: vertex-ai-imagen
Version: 1.1.4
Summary: Simple and clean Python client for Google Cloud Vertex AI Imagen
Author-email: Kevin Park <kevinpark1981@gmail.com>
Maintainer-email: Kevin Park <kevinpark1981@gmail.com>
License: MIT
Project-URL: Homepage, https://github.com/realcoding2003/vertex-ai-imagen
Project-URL: Repository, https://github.com/realcoding2003/vertex-ai-imagen
Project-URL: Issues, https://github.com/realcoding2003/vertex-ai-imagen/issues
Project-URL: Documentation, https://github.com/realcoding2003/vertex-ai-imagen/blob/master/README.md
Keywords: vertex-ai,imagen,google-cloud,ai,image-generation,machine-learning
Classifier: Development Status :: 5 - Production/Stable
Classifier: Intended Audience :: Developers
Classifier: Operating System :: OS Independent
Classifier: Programming Language :: Python :: 3
Classifier: Programming Language :: Python :: 3.8
Classifier: Programming Language :: Python :: 3.9
Classifier: Programming Language :: Python :: 3.10
Classifier: Programming Language :: Python :: 3.11
Classifier: Programming Language :: Python :: 3.12
Classifier: Topic :: Software Development :: Libraries :: Python Modules
Classifier: Topic :: Scientific/Engineering :: Artificial Intelligence
Classifier: Topic :: Multimedia :: Graphics
Requires-Python: >=3.8
License-File: LICENSE
Requires-Dist: requests>=2.31.0
Requires-Dist: google-auth>=2.23.0
Requires-Dist: google-auth-oauthlib>=1.1.0
Requires-Dist: google-auth-httplib2>=0.1.1
Requires-Dist: python-dotenv>=1.0.0
Provides-Extra: dev
Requires-Dist: pytest>=6.0; extra == "dev"
Requires-Dist: pytest-asyncio>=0.18.0; extra == "dev"
Requires-Dist: black>=21.0.0; extra == "dev"
Requires-Dist: flake8>=3.8.0; extra == "dev"
Requires-Dist: mypy>=0.910; extra == "dev"
Requires-Dist: coverage>=6.0; extra == "dev"
Provides-Extra: jupyter
Requires-Dist: ipython>=7.0; extra == "jupyter"
Requires-Dist: jupyter>=1.0; extra == "jupyter"
Dynamic: license-file
